Workbook

Sheet Summary
A1: FRAMS testing summary
A2: 18 October 2026
A4: Category | B4: Executed | C4: Passed | D4: Failed | E4: Blocked | F4: Not Executed
A5: Unit Testing | B5: =COUNTIF('All Test Cases'!B:B,A5) | C5: =COUNTIFS('All Test Cases'!B:B,A5,'All Test Cases'!F:F,"PASS") | D5: =COUNTIFS('All Test Cases'!B:B,A5,'All Test Cases'!F:F,"FAIL") | E5: =COUNTIFS('All Test Cases'!B:B,A5,'All Test Cases'!F:F,"BLOCKED") | F5: =COUNTIFS('All Test Cases'!B:B,A5,'All Test Cases'!F:F,"NOT EXECUTED")
A6: Integration Testing | B6: =COUNTIF('All Test Cases'!B:B,A6) | C6: =COUNTIFS('All Test Cases'!B:B,A6,'All Test Cases'!F:F,"PASS") | D6: =COUNTIFS('All Test Cases'!B:B,A6,'All Test Cases'!F:F,"FAIL") | E6: =COUNTIFS('All Test Cases'!B:B,A6,'All Test Cases'!F:F,"BLOCKED") | F6: =COUNTIFS('All Test Cases'!B:B,A6,'All Test Cases'!F:F,"NOT EXECUTED")
A7: System Testing | B7: =COUNTIF('All Test Cases'!B:B,A7) | C7: =COUNTIFS('All Test Cases'!B:B,A7,'All Test Cases'!F:F,"PASS") | D7: =COUNTIFS('All Test Cases'!B:B,A7,'All Test Cases'!F:F,"FAIL") | E7: =COUNTIFS('All Test Cases'!B:B,A7,'All Test Cases'!F:F,"BLOCKED") | F7: =COUNTIFS('All Test Cases'!B:B,A7,'All Test Cases'!F:F,"NOT EXECUTED")
A8: Security Testing | B8: =COUNTIF('All Test Cases'!B:B,A8) | C8: =COUNTIFS('All Test Cases'!B:B,A8,'All Test Cases'!F:F,"PASS") | D8: =COUNTIFS('All Test Cases'!B:B,A8,'All Test Cases'!F:F,"FAIL") | E8: =COUNTIFS('All Test Cases'!B:B,A8,'All Test Cases'!F:F,"BLOCKED") | F8: =COUNTIFS('All Test Cases'!B:B,A8,'All Test Cases'!F:F,"NOT EXECUTED")
A9: Penetration Testing | B9: =COUNTIF('All Test Cases'!B:B,A9) | C9: =COUNTIFS('All Test Cases'!B:B,A9,'All Test Cases'!F:F,"PASS") | D9: =COUNTIFS('All Test Cases'!B:B,A9,'All Test Cases'!F:F,"FAIL") | E9: =COUNTIFS('All Test Cases'!B:B,A9,'All Test Cases'!F:F,"BLOCKED") | F9: =COUNTIFS('All Test Cases'!B:B,A9,'All Test Cases'!F:F,"NOT EXECUTED")
A10: PayMongo Testing | B10: =COUNTIF('All Test Cases'!B:B,A10) | C10: =COUNTIFS('All Test Cases'!B:B,A10,'All Test Cases'!F:F,"PASS") | D10: =COUNTIFS('All Test Cases'!B:B,A10,'All Test Cases'!F:F,"FAIL") | E10: =COUNTIFS('All Test Cases'!B:B,A10,'All Test Cases'!F:F,"BLOCKED") | F10: =COUNTIFS('All Test Cases'!B:B,A10,'All Test Cases'!F:F,"NOT EXECUTED")
A11: TOTAL | B11: =SUM(B5:B10) | C11: =SUM(C5:C10) | D11: =SUM(D5:D10) | E11: =SUM(E5:E10) | F11: =SUM(F5:F10)
A13: Pass rate | B13: =IF((C11+D11)=0,0,C11/(C11+D11)) | C13: Denominator is passed plus failed. Blocked cases are excluded.
A15: Distinct test cases | B15: =COUNTA('All Test Cases'!A5:A500)
A17: Major confirmed findings
A18: F-001 zero or negative term is charged as one month; F-002 unencoded expense message; F-003 loan status changes without CSRF; F-004 security headers missing; F-005 local error display shows a filesystem path; F-007 loans outstanding card does not subtract payments.
A20: Limitations
A21: Live PayMongo payment creation and inbound webhook delivery were blocked. The live key was not used.

Sheet All Test Cases
A4: Test Case ID | B4: Category | C4: Scenario | D4: Expected Result | E4: Actual Result | F4: Status | G4: Evidence Filename | H4: Remarks
A5: UT-001 | B5: Unit Testing | C5: Standard monthly interest rate | D5: 5.0 percent | E5: 5 | F5: PASS | G5: logs/cli_test_execution.log
A6: UT-002 | B6: Unit Testing | C6: Twelve-month interest breakdown | D6: monthly 500.00, interest 6000.00, payable 16000.00 | E6: {"monthly_interest":500,"total_interest":6000,"total_payable":16000} | F6: PASS | G6: logs/cli_test_execution.log | H6: Formula: monthly = principal x rate/100; total interest = monthly x months; payable = principal + total interest.
A7: UT-003 | B7: Unit Testing | C7: Three-month interest breakdown | D7: monthly 500.00, interest 1500.00, payable 11500.00 | E7: {"monthly_interest":500,"total_interest":1500,"total_payable":11500} | F7: PASS | G7: logs/cli_test_execution.log
A8: UT-004 | B8: Unit Testing | C8: Zero principal | D8: all amounts 0.00 | E8: {"monthly_interest":0,"total_interest":0,"total_payable":0} | F8: PASS | G8: logs/cli_test_execution.log
A9: UT-005 | B9: Unit Testing | C9: Negative principal | D9: payable is 0.00 | E9: {"monthly_interest":0,"total_interest":0,"total_payable":0} | F9: PASS | G9: logs/cli_test_execution.log | H9: The implementation clamps principal with max(0, amount) instead of throwing.
A10: UT-006 | B10: Unit Testing | C10: Negative interest rate | D10: interest 0.00 and payable 8000.00 | E10: {"monthly_interest":0,"total_interest":0,"total_payable":8000} | F10: PASS | G10: logs/cli_test_execution.log | H10: Negative rates are clamped to zero.
A11: UT-007 | B11: Unit Testing | C11: Zero loan duration | D11: Invalid duration is rejected or does not create one month of interest. | E11: {"monthly_interest":500,"total_interest":500,"total_payable":10500} | F11: FAIL | G11: logs/cli_test_execution.log | H11: max(1, term) coerces zero months to one month and charges interest of 500.00.
A12: UT-008 | B12: Unit Testing | C12: Negative loan duration | D12: Invalid duration does not produce a one-month charge. | E12: {"monthly_interest":500,"total_interest":500,"total_payable":10500} | F12: FAIL | G12: logs/cli_test_execution.log | H12: Same coercion as UT-007.
A13: UT-009 | B13: Unit Testing | C13: Decimal rounding | D13: monthly 5.02, interest 15.05, payable 115.38 | E13: {"monthly_interest":5.02,"total_interest":15.05,"total_payable":115.38} | F13: PASS | G13: logs/cli_test_execution.log | H13: Each returned field is rounded separately. Rounded monthly interest times months is 15.06, while total interest remains 15.05.
A14: UT-010 | B14: Unit Testing | C14: Policy maximum principal | D14: monthly 25000.00, interest 300000.00, payable 800000.00 | E14: {"monthly_interest":25000,"total_interest":300000,"total_payable":800000} | F14: PASS | G14: logs/cli_test_execution.log
A15: UT-011 | B15: Unit Testing | C15: Loan term label parsing | D15: 12 | E15: 12 | F15: PASS | G15: logs/cli_test_execution.log
A16: UT-012 | B16: Unit Testing | C16: Non-numeric loan term | D16: 0 | E16: 0 | F16: PASS | G16: logs/cli_test_execution.log
A17: UT-013 | B17: Unit Testing | C17: Numeric zero term parsing | D17: The parser returns 1 because numeric input uses max(1, value). | E17: 1 | F17: PASS | G17: logs/cli_test_execution.log | H17: This matches the coercion observed in UT-007.
A18: UT-014 | B18: Unit Testing | C18: Payment frequency normalization | D18: semi-monthly, weekly, monthly | E18: checked three labels | F18: PASS | G18: logs/cli_test_execution.log
A19: UT-015 | B19: Unit Testing | C19: Installment counts | D19: 3, 12, 6, and 60 | E19: monthly 3, weekly 12, semi-monthly 6, daily 60 | F19: PASS | G19: logs/cli_test_execution.log | H19: Daily count without explicit dates is term months times 30.
A20: UT-016 | B20: Unit Testing | C20: Monthly due date | D20: 2026-03-15 | E20: 2026-03-15 | F20: PASS | G20: logs/cli_test_execution.log
A21: UT-017 | B21: Unit Testing | C21: Penalty rates by frequency | D21: 1, 2, 3, and 5 percent | E21: 1, 2, 3, 5 | F21: PASS | G21: logs/cli_test_execution.log
A22: UT-018 | B22: Unit Testing | C22: Installment amount from total payable | D22: 3833.33 | E22: 3833.33 | F22: PASS | G22: logs/cli_test_execution.log
A23: UT-019 | B23: Unit Testing | C23: Scheduled installment override | D23: 4000.00 | E23: 4000 | F23: PASS | G23: logs/cli_test_execution.log
A24: UT-020 | B24: Unit Testing | C24: Password policy | D24: true, false, false | E24: valid accepted; short and alphanumeric rejected | F24: PASS | G24: logs/cli_test_execution.log
A25: UT-021 | B25: Unit Testing | C25: Password verification | D25: hash matches; wrong password and plaintext storage do not | E25: hash match true; plaintext comparison false | F25: PASS | G25: logs/cli_test_execution.log
A26: UT-022 | B26: Unit Testing | C26: CSRF token comparison | D26: true, false, false | E26: matching accepted; mismatch and empty rejected | F26: PASS | G26: logs/cli_test_execution.log
A27: UT-023 | B27: Unit Testing | C27: Valid webhook signature | D27: true | E27: true | F27: PASS | G27: logs/cli_test_execution.log | H27: Local function test. No PayMongo request.
A28: UT-024 | B28: Unit Testing | C28: Invalid webhook signature | D28: false | E28: false | F28: PASS | G28: logs/cli_test_execution.log
A29: UT-025 | B29: Unit Testing | C29: Missing webhook signature | D29: false | E29: false | F29: PASS | G29: logs/cli_test_execution.log
A30: UT-026 | B30: Unit Testing | C30: Expired webhook timestamp | D30: false | E30: false | F30: PASS | G30: logs/cli_test_execution.log
A31: UT-027 | B31: Unit Testing | C31: Malformed webhook JSON | D31: null | E31: null | F31: PASS | G31: logs/cli_test_execution.log
A32: UT-028 | B32: Unit Testing | C32: Valid webhook event parse | D32: id and type extracted | E32: evt_parse payment.paid | F32: PASS | G32: logs/cli_test_execution.log
A33: UT-029 | B33: Unit Testing | C33: Webhook amount match | D33: true then false | E33: match/no-match | F33: PASS | G33: logs/cli_test_execution.log
A34: UT-030 | B34: Unit Testing | C34: QR image URL allow list | D34: only the PayMongo HTTPS URL is safe | E34: safe=yes unsafe-accepted=no | F34: PASS | G34: logs/cli_test_execution.log
A35: UT-031 | B35: Unit Testing | C35: Proposed monthly payment | D35: 1333.33 | E35: 1333.33 | F35: PASS | G35: logs/cli_test_execution.log | H35: 16000 / 12 = 1333.333..., rounded to 1333.33.
A36: UT-032 | B36: Unit Testing | C36: Maximum principal from payment | D36: approximately 9999.98 | E36: 9999.98 | F36: PASS | G36: logs/cli_test_execution.log | H36: Rounding of the forward payment prevents an exact 10000 reverse value.
A37: UT-033 | B37: Unit Testing | C37: Loan amount policy clamp | D37: 3000.00 | E37: 3000 | F37: PASS | G37: logs/cli_test_execution.log
A38: UT-034 | B38: Unit Testing | C38: Employment length parsing | D38: 24 and 2 | E38: 24 and 2 | F38: PASS | G38: logs/cli_test_execution.log
A39: UT-035 | B39: Unit Testing | C39: Eligible affordability estimate | D39: Eligible | E39: Eligible | F39: PASS | G39: logs/cli_test_execution.log | H39: DTI after observed: 11.11
A40: UT-036 | B40: Unit Testing | C40: Incomplete eligibility input | D40: Not Eligible and status_code incomplete | E40: Not Eligible/incomplete | F40: PASS | G40: logs/cli_test_execution.log
A41: UT-037 | B41: Unit Testing | C41: DTI above policy limit | D41: Not Eligible | E41: Not Eligible DTI 66.67 | F41: PASS | G41: logs/cli_test_execution.log
A42: UT-038 | B42: Unit Testing | C42: Conditional eligibility | D42: Conditionally Eligible | E42: Conditionally Eligible | F42: PASS | G42: logs/cli_test_execution.log
A43: UT-039 | B43: Unit Testing | C43: Existing debt blocks the wizard | D43: a non-empty blocking message | E43: blocked | F43: PASS | G43: logs/cli_test_execution.log
A44: UT-040 | B44: Unit Testing | C44: Missing upload file | D44: ok false | E44: rejected | F44: PASS | G44: logs/cli_test_execution.log | H44: No file uploaded.
A45: UT-041 | B45: Unit Testing | C45: No penalty before the due date | D45: 0.00 | E45: 0 | F45: PASS | G45: logs/cli_test_execution.log
A46: UT-042 | B46: Unit Testing | C46: Initial loan balance | D46: payable 11500, paid 0, remaining 11500 | E46: {"total_payable":11500,"total_paid":0,"penalty_paid":0,"remaining_balance":11500,"penalty_due":0,"total_amount_due":11500} | F46: PASS | G46: logs/cli_test_execution.log
A47: UT-043 | B47: Unit Testing | C47: Zero payment amount | D47: InvalidArgumentException | E47: rejected | F47: PASS | G47: logs/cli_test_execution.log
A48: UT-044 | B48: Unit Testing | C48: Negative payment amount | D48: rejected as a non-positive amount | E48: rejected | F48: PASS | G48: logs/cli_test_execution.log | H48: The validator clamps the input to zero and then rejects it.
A49: UT-045 | B49: Unit Testing | C49: Overpayment rejection | D49: exception and payment count unchanged | E49: rejected; count 0 to 0 | F49: PASS | G49: logs/cli_test_execution.log
A50: IT-001 | B50: Integration Testing | C50: Administrator login | D50: session role Admin | E50: Admin session | F50: PASS | G50: logs/cli_test_execution.log
A51: IT-002 | B51: Integration Testing | C51: Collector login and role | D51: collector true, admin false | E51: collector only | F51: PASS | G51: logs/cli_test_execution.log
A52: IT-003 | B52: Integration Testing | C52: Collector client scope | D52: true for A and false for B | E52: A=yes B=no | F52: PASS | G52: logs/cli_test_execution.log
A53: IT-004 | B53: Integration Testing | C53: Collector loan scope | D53: true for A and false for B | E53: A=yes B=no | F53: PASS | G53: logs/cli_test_execution.log
A54: IT-005 | B54: Integration Testing | C54: Borrower authentication boundary | D54: borrower function returns the user; staff login returns false | E54: borrower-ok/staff-rejected | F54: PASS | G54: logs/cli_test_execution.log
A55: IT-006 | B55: Integration Testing | C55: Inactive account | D55: false | E55: rejected | F55: PASS | G55: logs/cli_test_execution.log
A56: IT-007 | B56: Integration Testing | C56: Wrong password | D56: false and logged out | E56: Isolated retest passed: the credential was rejected and the session was cleared. | F56: PASS | G56: logs/cli_test_execution.log | H56: The first CLI run reported a failure because the test script had already written output, so PHP could not complete session_regenerate_id or session_destroy. A second process with output buffering confirmed the application behavior. Application code was not changed.
A57: IT-008 | B57: Integration Testing | C57: Borrower, client, and loan link | D57: one linked row | E57: client 20 loan 29 | F57: PASS | G57: logs/cli_test_execution.log
A58: IT-009 | B58: Integration Testing | C58: Invalid loan reference | D58: the insert fails or is rolled back and no row remains | E58: inserted; remaining 0 | F58: PASS | G58: logs/cli_test_execution.log | H58: No foreign key stopped the insert; the test transaction was rolled back.
A59: IT-010 | B59: Integration Testing | C59: Cash payment posts to the loan | D59: receipt RJRR-*, method Cash, remaining 7666.67 | E59: receipt RJRR-20261018-000001 balance 7666.67 | F59: PASS | G59: logs/cli_test_execution.log | H59: Direct function call on the isolated database. Email was not sent because the synthetic client email is null.
A60: IT-011 | B60: Integration Testing | C60: Rejected payment rolls back | D60: exception and same payment count | E60: rejected; count 1 to 1 | F60: PASS | G60: logs/cli_test_execution.log
A61: IT-012 | B61: Integration Testing | C61: Schedule status after payment | D61: Paid, Upcoming, Upcoming | E61: Paid, Upcoming, Upcoming | F61: PASS | G61: logs/cli_test_execution.log
A62: IT-013 | B62: Integration Testing | C62: Logout clears the session | D62: isLoggedIn false | E62: Isolated retest passed: the credential was rejected and the session was cleared. | F62: PASS | G62: logs/cli_test_execution.log | H62: The first CLI run reported a failure because the test script had already written output, so PHP could not complete session_regenerate_id or session_destroy. A second process with output buffering confirmed the application behavior. Application code was not changed.
A63: ST-001 | B63: System Testing | C63: Staff login page loads | D63: HTTP 200 and the staff welcome heading | E63: HTTP 200 contains Welcome back | F63: PASS | G63: 03_System_Testing/screenshots/ST-001_staff_login.png
A64: ST-002 | B64: System Testing | C64: Invalid staff login | D64: HTTP 200 and Invalid username or password | E64: HTTP 200 error shown | F64: PASS | G64: 03_System_Testing/screenshots/ST-002_invalid_login.png
A65: ST-003 | B65: System Testing | C65: Missing login fields | D65: Please enter both username and password | E65: validation message shown | F65: PASS | G65: logs/http_test_execution.log | H65: The browser may also require the fields before submit. This request was sent directly.
A66: ST-004 | B66: System Testing | C66: Administrator login and dashboard | D66: redirect to dashboard and Executive Dashboard | E66: login HTTP 302; dashboard HTTP 200 dashboard shown | F66: PASS | G66: 03_System_Testing/screenshots/ST-004_admin_dashboard.png
A67: ST-005 | B67: System Testing | C67: Administrator client list | D67: HTTP 200 and Synthetic BorrowerA | E67: client visible | F67: PASS | G67: 03_System_Testing/screenshots/ST-005_admin_clients.png
A68: ST-006 | B68: System Testing | C68: Administrator loan list | D68: The loan list shows the synthetic borrowers. | E68: Synthetic BorrowerA (loan 29) and Synthetic BorrowerB (loan 30) are listed. The table shows the borrower name rather than the loan-number string. | F68: PASS | G68: 03_System_Testing/screenshots/ST-006_admin_loans_table.png | H68: The first assertion looked for the text FRAMS-TEST-A. That string is not rendered in the loans table. The saved page HTML and the browser screenshot show both synthetic borrowers, so the result is PASS.
A69: ST-007 | B69: System Testing | C69: Administrator payment records | D69: page contains a receipt or the cash amount | E69: payment visible | F69: PASS | G69: 03_System_Testing/screenshots/ST-007_admin_payments.png
A70: ST-008 | B70: System Testing | C70: Administrator reports | D70: HTTP 200 and a report heading | E70: HTTP 200 | F70: PASS | G70: 03_System_Testing/screenshots/ST-008_admin_reports.png
A71: ST-009 | B71: System Testing | C71: User management page | D71: HTTP 200 and synthetic usernames | E71: users visible | F71: PASS | G71: 03_System_Testing/screenshots/ST-009_admin_users.png
A72: ST-010 | B72: System Testing | C72: Collector login and dashboard | D72: HTTP 302 then collector dashboard content | E72: login 302 dashboard 200 | F72: PASS | G72: 03_System_Testing/screenshots/ST-010_collector_dashboard.png
A73: ST-011 | B73: System Testing | C73: Collector loads the assigned loan | D73: JSON success true | E73: success true | F73: PASS | G73: logs/http_test_execution.log
A74: ST-012 | B74: System Testing | C74: Collector records a cash payment | D74: payment count increases by 1 | E74: HTTP 302; count 1 to 2; paid 7666.66 | F74: PASS | G74: 03_System_Testing/screenshots/ST-012_cash_payment_result.png | H74: Form submission against the isolated database.
A75: ST-013 | B75: System Testing | C75: Non-cash QR start fails closed | D75: no succeeded 100 peso QR transaction | E75: HTTP 200; succeeded-100 rows 0; body has error yes | F75: PASS | G75: 03_System_Testing/screenshots/ST-013_qr_error.png | H75: Invalid test key. No live PayMongo call. The provider returned HTTP 401 inside the application error.
A76: ST-014 | B76: System Testing | C76: Borrower login and dashboard | D76: dashboard HTTP 200 | E76: login 302 dashboard 200 | F76: PASS | G76: 03_System_Testing/screenshots/ST-014_borrower_dashboard.png
A77: ST-015 | B77: System Testing | C77: Borrower loan view | D77: loan number visible | E77: loan visible | F77: PASS | G77: 03_System_Testing/screenshots/ST-015_borrower_loan.png
A78: ST-016 | B78: System Testing | C78: Borrower payment history | D78: RJRR receipt visible | E78: receipt visible | F78: PASS | G78: 03_System_Testing/screenshots/ST-016_borrower_history.png
A79: ST-017 | B79: System Testing | C79: Borrower logout | D79: dashboard redirects to login | E79: logout 302; next 302 location borrower_login_lending.php | F79: PASS | G79: 03_System_Testing/screenshots/ST-017_after_logout.png
A80: ST-018 | B80: System Testing | C80: Unauthenticated dashboard | D80: HTTP 302 to login | E80: HTTP 302 | F80: PASS | G80: logs/http_test_execution.log
A81: ST-019 | B81: System Testing | C81: Borrower denied admin dashboard | D81: redirect away from Executive Dashboard | E81: HTTP 302 dashboard not rendered | F81: PASS | G81: logs/http_test_execution.log
A82: ST-020 | B82: System Testing | C82: Collector denied expenses | D82: HTTP 403 | E82: HTTP 403 | F82: PASS | G82: 03_System_Testing/screenshots/ST-020_collector_forbidden.png
A83: SEC-001 | B83: Security Testing | C83: Password storage | D83: bcrypt hash that verifies | E83: bcrypt hash verifies | F83: PASS | G83: logs/cli_test_execution.log | H83: The hash value is not recorded.
A84: SEC-002 | B84: Security Testing | C84: Login SQL injection payload | D84: false | E84: Isolated retest passed: the credential was rejected and the session was cleared. | F84: PASS | G84: logs/cli_test_execution.log | H84: The first CLI run reported a failure because the test script had already written output, so PHP could not complete session_regenerate_id or session_destroy. A second process with output buffering confirmed the application behavior. Application code was not changed.
A85: SEC-003 | B85: Security Testing | C85: Output encoding helper | D85: encoded angle brackets | E85: &lt;script&gt;alert(&#039;x&#039;)&lt;/script&gt; | F85: PASS | G85: logs/cli_test_execution.log | H85: Page-level reflection is tested over HTTP.
A86: SEC-004 | B86: Security Testing | C86: Wrong CSRF token | D86: false | E86: rejected | F86: PASS | G86: logs/cli_test_execution.log
A87: SEC-005 | B87: Security Testing | C87: Collector cannot pay another loan | D87: payment count unchanged and not assigned message | E87: count 1 to 1; assigned message yes | F87: PASS | G87: logs/http_test_execution.log
A88: SEC-006 | B88: Security Testing | C88: Collector loan lookup IDOR | D88: success false and no borrower name | E88: success false | F88: PASS | G88: logs/http_test_execution.log
A89: SEC-007 | B89: Security Testing | C89: Borrower receipt IDOR | D89: redirect away from the other receipt | E89: HTTP 302 other borrower not shown | F89: PASS | G89: logs/http_test_execution.log | H89: HTTP 302.
A90: SEC-008 | B90: Security Testing | C90: Login SQL injection over HTTP | D90: invalid credentials and no SQL syntax error | E90: rejected | F90: PASS | G90: 04_Security_Testing/screenshots/SEC-008_sqli_login.png
A91: SEC-009 | B91: Security Testing | C91: Login username encoding | D91: encoded attribute value | E91: encoded | F91: PASS | G91: logs/http_test_execution.log
A92: SEC-010 | B92: Security Testing | C92: Reflected HTML in expense message | D92: marker encoded and not present as HTML | E92: raw HTML reflected | F92: FAIL | G92: 04_Security_Testing/screenshots/SEC-010_reflected_message.png | H92: Authenticated reflected output.
A93: SEC-011 | B93: Security Testing | C93: Expense search SQL injection | D93: HTTP 200 and no SQLSTATE | E93: HTTP 200 no sql error | F93: PASS | G93: logs/http_test_execution.log | H93: The search uses a bound LIKE parameter.
A94: SEC-012 | B94: Security Testing | C94: Payment without CSRF token | D94: HTTP 419 and payment count unchanged | E94: HTTP 419; count 2 to 2 | F94: PASS | G94: logs/http_test_execution.log
A95: SEC-013 | B95: Security Testing | C95: Payment with incorrect CSRF token | D95: HTTP 419 and payment count unchanged | E95: HTTP 419; count 2 to 2 | F95: PASS | G95: logs/http_test_execution.log
A96: SEC-014 | B96: Security Testing | C96: Loan status change without CSRF token | D96: request rejected and status unchanged | E96: HTTP 200; status Active to Overdue | F96: FAIL | G96: logs/http_test_execution.log | H96: Observed behavior is the test result. Status will be restored to Active after evidence is saved if it changed.
A97: SEC-015 | B97: Security Testing | C97: Session cookie attributes | D97: HttpOnly present | E97: HttpOnly yes; Secure no | F97: PASS | G97: logs/http_test_execution.log | H97: Secure is absent because this server is HTTP. lendingConfigureRuntime sets Secure only when HTTPS is detected.
A98: SEC-016 | B98: Security Testing | C98: Security response headers | D98: X-Frame-Options, X-Content-Type-Options, Content-Security-Policy, and Referrer-Policy | E98: missing X-Frame-Options, X-Content-Type-Options, Content-Security-Policy, Referrer-Policy | F98: FAIL | G98: logs/http_test_execution.log
A99: SEC-017 | B99: Security Testing | C99: Excessive login length | D99: invalid credentials or normal validation, no SQLSTATE | E99: no sql error HTTP 200 | F99: PASS | G99: logs/http_test_execution.log
A100: PEN-001 | B100: Penetration Testing | C100: Direct URL to user management | D100: redirect to login | E100: HTTP 302 | F100: PASS | G100: 05_Penetration_Testing/screenshots/PEN-001_anonymous_users.png
A101: PEN-002 | B101: Penetration Testing | C101: Direct URL to payments | D101: redirect to login | E101: HTTP 302 | F101: PASS | G101: logs/http_test_execution.log
A102: PEN-003 | B102: Penetration Testing | C102: Borrower direct URL to user management | D102: redirect and no user table | E102: HTTP 302 admin user not shown | F102: PASS | G102: logs/http_test_execution.log
A103: PEN-004 | B103: Penetration Testing | C103: Anonymous payment post | D103: redirect to login and payment count unchanged | E103: HTTP 302; count 3 to 3 | F103: PASS | G103: logs/http_test_execution.log
...

Sheet Security Findings
A1: Finding ID | B1: Category | C1: Affected component | D1: Description | E1: Severity | F1: Evidence | G1: Reproduction summary | H1: Recommendation | I1: Retest status
A2: F-001 | B2: Unit Testing | C2: calculateLoanInterestBreakdown | D2: A zero or negative loan term is coerced to one month, so the calculator charges one month of interest instead of rejecting the duration. | E2: Low | F2: 01_Unit_Testing/logs/cli_test_execution.log | G2: Call calculateLoanInterestBreakdown(10000, 5, 0). Observed total interest 500.00 and total payable 10500.00. | H2: Reject a term less than 1 at the calculator and at the application form before interest is stored. | I2: Not retested. Application code was not changed.
A3: F-002 | B3: Security Testing | C3: expenses_lending.php message query parameter | D3: The expenses page prints the message query parameter without encoding, so an authenticated user can be sent a link that injects HTML. | E3: Medium | F3: 04_Security_Testing/logs/http_test_execution.log | G3: Sign in as an administrator on the isolated server and open expenses_lending.php?message=FRAMSXSS<b>probe</b>&type=success. The response contains the raw b tag. | H3: Encode $message and $messageType with htmlspecialchars before output. Apply the same fix on the other pages that echo those variables. | I3: Not retested. Application code was not changed.
A4: F-003 | B4: Security Testing | C4: loans_lending.php update_status | D4: An authenticated administrator request can change a loan status without a CSRF token. | E4: Medium | F4: 04_Security_Testing/logs/http_test_execution.log | G4: Sign in as the synthetic administrator and POST update_status, loan_id, and status=Overdue to loans_lending.php without _csrf_token. The loan status changes. | H4: Call csrfRequireValid() before update_status, as payments_lending.php already does. | I4: Not retested. The synthetic loan status is restored after the demonstration. Application code was not changed.
A5: F-004 | B5: Security Testing | C5: HTTP response headers | D5: Login responses do not set X-Frame-Options, X-Content-Type-Options, Content-Security-Policy, Referrer-Policy. | E5: Low | F5: 04_Security_Testing/logs/http_test_execution.log | G5: GET login_lending.php on the isolated server and inspect the response headers. | H5: Send the missing headers from a shared include used by every page. | I5: Not retested. Application code was not changed.
A6: F-005 | B6: Security Testing | C6: users_lending.php | D6: With APP_ENV=local, display_errors is on. The user list passes a null email to htmlspecialchars and prints a deprecation warning that includes the application filesystem path. | E6: Low | F6: 04_Security_Testing/screenshots/SEC-018_error_disclosure.png | G6: Sign in as the synthetic administrator on the isolated server and open users_lending.php. The email column shows the deprecation text and path. | H6: Pass an empty string when email is null, and set APP_ENV=production with display_errors off on any shared server. | I6: Not retested. Application code was not changed.
A7: F-006 | B7: PayMongo Testing | C7: PayMongo configuration | D7: The project .env sets PAYMONGO_MODE=live and contains a live secret key and live public key. PAYMONGO_WEBHOOK_SECRET is empty. No live API request was sent during this test. | E7: High | F7: 06_PayMongo_Testing/logs/environment_probe.txt | G7: Read the configuration keys without printing their values. Mode is live, the secret key prefix is sk_live, and the webhook secret is empty. | H7: Use test keys and PAYMONGO_MODE=test on this local workstation. Configure the matching webhook secret before accepting QR Ph events. Do not commit .env. | I7: Not changed. Live credentials were not used.
A8: F-007 | B8: System Testing | C8: loans_lending.php outstanding statistic | D8: The loans page outstanding figure sums total_payable for loans whose stored status is not Paid. It does not subtract recorded payments. After 10,416.66 in collections the card still showed 17,000.00, while the reports page outstanding was 6,583.34. | E8: Medium | F8: 03_System_Testing/screenshots/ST-006_admin_loans.png | G8: Record partial payments on the isolated loans and compare the loans page outstanding card with the reports page outstanding card. | H8: Calculate outstanding as total payable minus recorded payments, consistent with calculateLoanBalanceSummary. | I8: Not retested. Application code was not changed.

Sheet Evidence Register
A1: Evidence ID | B1: Testing Category | C1: Related Test Case ID | D1: Filename | E1: Evidence Type | F1: Description | G1: Execution Date | H1: Evidence Status
A2: E-001 | B2: Unit Testing | D2: cli_test_execution.log | E2: log | F2: 01_Unit_Testing/logs/cli_test_execution.log | G2: 18 October 2026 | H2: Present
A3: E-002 | B3: Unit Testing | D3: report.md | E3: md | F3: 01_Unit_Testing/report.md | G3: 18 October 2026 | H3: Present
A4: E-003 | B4: Unit Testing | D4: NO_BROWSER_SCREENSHOT.txt | E4: txt | F4: 01_Unit_Testing/screenshots/NO_BROWSER_SCREENSHOT.txt | G4: 18 October 2026 | H4: Present
A5: E-004 | B5: Unit Testing | D5: cli_results.json | E5: json | F5: 01_Unit_Testing/test_results/cli_results.json | G5: 18 October 2026 | H5: Present
A6: E-005 | B6: Unit Testing | D6: published_results.json | E6: json | F6: 01_Unit_Testing/test_results/published_results.json | G6: 18 October 2026 | H6: Present
A7: E-006 | B7: Integration Testing | D7: cli_test_execution.log | E7: log | F7: 02_Integration_Testing/logs/cli_test_execution.log | G7: 18 October 2026 | H7: Present
A8: E-007 | B8: Integration Testing | D8: report.md | E8: md | F8: 02_Integration_Testing/report.md | G8: 18 October 2026 | H8: Present
A9: E-008 | B9: Integration Testing | D9: NO_BROWSER_SCREENSHOT.txt | E9: txt | F9: 02_Integration_Testing/screenshots/NO_BROWSER_SCREENSHOT.txt | G9: 18 October 2026 | H9: Present
A10: E-009 | B10: Integration Testing | D10: cli_results.json | E10: json | F10: 02_Integration_Testing/test_results/cli_results.json | G10: 18 October 2026 | H10: Present
A11: E-010 | B11: Integration Testing | D11: published_results.json | E11: json | F11: 02_Integration_Testing/test_results/published_results.json | G11: 18 October 2026 | H11: Present
A12: E-011 | B12: System Testing | D12: http_test_execution.log | E12: log | F12: 03_System_Testing/logs/http_test_execution.log | G12: 18 October 2026 | H12: Present
A13: E-012 | B13: System Testing | D13: loans_page.html | E13: html | F13: 03_System_Testing/logs/loans_page.html | G13: 18 October 2026 | H13: Present
A14: E-013 | B14: System Testing | D14: report.md | E14: md | F14: 03_System_Testing/report.md | G14: 18 October 2026 | H14: Present
A15: E-014 | B15: System Testing | C15: ST-001 | D15: ST-001_staff_login.png | E15: png | F15: 03_System_Testing/screenshots/ST-001_staff_login.png | G15: 18 October 2026 | H15: Present
A16: E-015 | B16: System Testing | C16: ST-002 | D16: ST-002_invalid_login.png | E16: png | F16: 03_System_Testing/screenshots/ST-002_invalid_login.png | G16: 18 October 2026 | H16: Present
A17: E-016 | B17: System Testing | C17: ST-004 | D17: ST-004_admin_dashboard.png | E17: png | F17: 03_System_Testing/screenshots/ST-004_admin_dashboard.png | G17: 18 October 2026 | H17: Present
A18: E-017 | B18: System Testing | C18: ST-005 | D18: ST-005_admin_clients.png | E18: png | F18: 03_System_Testing/screenshots/ST-005_admin_clients.png | G18: 18 October 2026 | H18: Present
A19: E-018 | B19: System Testing | C19: ST-006 | D19: ST-006_admin_loans.png | E19: png | F19: 03_System_Testing/screenshots/ST-006_admin_loans.png | G19: 18 October 2026 | H19: Present
A20: E-019 | B20: System Testing | C20: ST-006 | D20: ST-006_admin_loans_table.png | E20: png | F20: 03_System_Testing/screenshots/ST-006_admin_loans_table.png | G20: 18 October 2026 | H20: Present
A21: E-020 | B21: System Testing | C21: ST-007 | D21: ST-007_admin_payments.png | E21: png | F21: 03_System_Testing/screenshots/ST-007_admin_payments.png | G21: 18 October 2026 | H21: Present
A22: E-021 | B22: System Testing | C22: ST-008 | D22: ST-008_admin_reports.png | E22: png | F22: 03_System_Testing/screenshots/ST-008_admin_reports.png | G22: 18 October 2026 | H22: Present
A23: E-022 | B23: System Testing | C23: ST-009 | D23: ST-009_admin_users.png | E23: png | F23: 03_System_Testing/screenshots/ST-009_admin_users.png | G23: 18 October 2026 | H23: Present
A24: E-023 | B24: System Testing | C24: ST-010 | D24: ST-010_collector_dashboard.png | E24: png | F24: 03_System_Testing/screenshots/ST-010_collector_dashboard.png | G24: 18 October 2026 | H24: Present
A25: E-024 | B25: System Testing | C25: ST-014 | D25: ST-014_borrower_dashboard.png | E25: png | F25: 03_System_Testing/screenshots/ST-014_borrower_dashboard.png | G25: 18 October 2026 | H25: Present
A26: E-025 | B26: System Testing | C26: ST-015 | D26: ST-015_borrower_loan.png | E26: png | F26: 03_System_Testing/screenshots/ST-015_borrower_loan.png | G26: 18 October 2026 | H26: Present
... A29: E-028 | B29: System Testing | C29: ST-020 | D29: ST-020_collector_forbidden.png | E29: png | F29: 03_System_Testing/screenshots/ST-020_collector_forbidden.png | G29: 18 October 2026 | H29: Present
A30: E-029 | B30: System Testing | D30: http_results.json | E30: json | F30: 03_System_Testing/test_results/http_results.json | G30: 18 October 2026 | H30: Present
A31: E-030 | B31: System Testing | D31: published_results.json | E31: json | F31: 03_System_Testing/test_results/published_results.json | G31: 18 October 2026 | H31: Present
A32: E-031 | B32: Security Testing | D32: cli_test_execution.log | E32: log | F32: 04_Security_Testing/logs/cli_test_execution.log | G32: 18 October 2026 | H32: Present
A33: E-032 | B33: Security Testing | D33: http_test_execution.log | E33: log | F33: 04_Security_Testing/logs/http_test_execution.log | G33: 18 October 2026 | H33: Present
A34: E-033 | B34: Security Testing | D34: sec010_alert_innerhtml.txt | E34: txt | F34: 04_Security_Testing/logs/sec010_alert_innerhtml.txt | G34: 18 October 2026 | H34: Present
A35: E-034 | B35: Security Testing | D35: report.md | E35: md | F35: 04_Security_Testing/report.md | G35: 18 October 2026 | H35: Present
A36: E-035 | B36: Security Testing | C36: SEC-010 | D36: SEC-010_reflected_message.png | E36: png | F36: 04_Security_Testing/screenshots/SEC-010_reflected_message.png | G36: 18 October 2026 | H36: Present
A37: E-036 | B37: Security Testing | C37: SEC-014 | D37: SEC-014_dashboard_overdue_count.png | E37: png | F37: 04_Security_Testing/screenshots/SEC-014_dashboard_overdue_count.png | G37: 18 October 2026 | H37: Present
A38: E-037 | B38: Security Testing | C38: SEC-014 | D38: SEC-014_status_visible_to_borrower.png | E38: png | F38: 04_Security_Testing/screenshots/SEC-014_status_visible_to_borrower.png | G38: 18 October 2026 | H38: Present
A39: E-038 | B39: Security Testing | C39: SEC-018 | D39: SEC-018_error_disclosure.png | E39: png | F39: 04_Security_Testing/screenshots/SEC-018_error_disclosure.png | G39: 18 October 2026 | H39: Present
A40: E-039 | B40: Security Testing | D40: cli_results.json | E40: json | F40: 04_Security_Testing/test_results/cli_results.json | G40: 18 October 2026 | H40: Present
A41: E-040 | B41: Security Testing | D41: http_results.json | E41: json | F41: 04_Security_Testing/test_results/http_results.json | G41: 18 October 2026 | H41: Present
A42: E-041 | B42: Security Testing | D42: published_results.json | E42: json | F42: 04_Security_Testing/test_results/published_results.json | G42: 18 October 2026 | H42: Present
A43: E-042 | B43: Penetration Testing | D43: http_test_execution.log | E43: log | F43: 05_Penetration_Testing/logs/http_test_execution.log | G43: 18 October 2026 | H43: Present
A44: E-043 | B44: Penetration Testing | D44: report.md | E44: md | F44: 05_Penetration_Testing/report.md | G44: 18 October 2026 | H44: Present
A45: E-044 | B45: Penetration Testing | C45: PEN-001 | D45: PEN-001_anonymous_users.png | E45: png | F45: 05_Penetration_Testing/screenshots/PEN-001_anonymous_users.png | G45: 18 October 2026 | H45: Present
A46: E-045 | B46: Penetration Testing | D46: http_results.json | E46: json | F46: 05_Penetration_Testing/test_results/http_results.json | G46: 18 October 2026 | H46: Present
A47: E-046 | B47: Penetration Testing | D47: published_results.json | E47: json | F47: 05_Penetration_Testing/test_results/published_results.json | G47: 18 October 2026 | H47: Present
A48: E-047 | B48: PayMongo Testing | D48: cli_test_execution.log | E48: log | F48: 06_PayMongo_Testing/logs/cli_test_execution.log | G48: 18 October 2026 | H48: Present
A49: E-048 | B49: PayMongo Testing | D49: environment_probe.txt | E49: txt | F49: 06_PayMongo_Testing/logs/environment_probe.txt | G49: 18 October 2026 | H49: Present
A50: E-049 | B50: PayMongo Testing | D50: http_test_execution.log | E50: log | F50: 06_PayMongo_Testing/logs/http_test_execution.log | G50: 18 October 2026 | H50: Present
A51: E-050 | B51: PayMongo Testing | D51: report.md | E51: md | F51: 06_PayMongo_Testing/report.md | G51: 18 October 2026 | H51: Present
A52: E-051 | B52: PayMongo Testing | C52: PM-005 | D52: PM-005_simulated_payment_listed.png | E52: png | F52: 06_PayMongo_Testing/screenshots/PM-005_simulated_payment_listed.png | G52: 18 October 2026 | H52: Present
A53: E-052 | B53: PayMongo Testing | D53: cli_results.json | E53: json | F53: 06_PayMongo_Testing/test_results/cli_results.json | G53: 18 October 2026 | H53: Present
A54: E-053 | B54: PayMongo Testing | D54: http_results.json | E54: json | F54: 06_PayMongo_Testing/test_results/http_results.json | G54: 18 October 2026 | H54: Present
A55: E-054 | B55: PayMongo Testing | D55: published_results.json | E55: json | F55: 06_PayMongo_Testing/test_results/published_results.json | G55: 18 October 2026 | H55: Present
A56: E-055 | B56: Package | D56: FINAL_TESTING_REPORT.docx | E56: docx | F56: FINAL_TESTING_REPORT.docx | G56: 18 October 2026 | H56: Present
A57: E-056 | B57: Package | D57: FINAL_TESTING_REPORT.md | E57: md | F57: FINAL_TESTING_REPORT.md | G57: 18 October 2026 | H57: Present
A58: E-057 | B58: Package | D58: FINAL_TESTING_REPORT.pdf | E58: pdf | F58: FINAL_TESTING_REPORT.pdf | G58: 18 October 2026 | H58: Present
A59: E-058 | B59: Package | D59: README.md | E59: md | F59: README.md | G59: 18 October 2026 | H59: Present
A60: E-059 | B60: Package | D60: SUMMARY_REPORT.md | E60: md | F60: SUMMARY_REPORT.md | G60: 18 October 2026 | H60: Present
A61: E-060 | B61: Package | D61: TESTING_RESULTS.xlsx | E61: xlsx | F61: TESTING_RESULTS.xlsx | G61: 18 October 2026 | H61: Present
